{
  "title": "מחזור מצבי ההרשאה עם Shift Tab: ממצב Manual ששואל תמיד, למצב Accept edits שעורך בלי לשאול, למצב Plan שחוקר ומציע תוכנית, וחזרה",
  "layout": { "type": "flow" },
  "components": [
    { "id": "manual", "type": "box", "label": "מצב Manual - שואל תמיד" },
    { "id": "accept", "type": "box", "label": "מצב Accept edits - בלי לשאול" },
    { "id": "plan", "type": "box", "label": "מצב Plan - חוקר ומציע" }
  ],
  "connections": [
    { "from": "manual", "to": "accept", "label": "Shift+Tab" },
    { "from": "accept", "to": "plan", "label": "Shift+Tab" },
    { "from": "plan", "to": "manual", "label": "Shift+Tab", "loop": true }
  ],
  "animation": {
    "step_seconds": 1.6,
    "steps": [
      { "active": ["manual"] },
      { "active": ["accept"], "edges": [0] },
      { "active": ["plan"], "edges": [1] },
      { "active": ["manual"], "edges": [2] }
    ]
  }
}
