{
  "title": "תרשים זרימה של התקפת Stored XSS: תגובה זדונית נשמרת בשרת, וכשאין סניטציה הסקריפט רץ אצל הקורבן וגונב את העוגייה",
  "layout": { "type": "flow" },
  "components": [
    { "id": "attacker", "type": "box", "label": "התוקף שולח תגובה זדונית" },
    { "id": "payload", "type": "code", "label": "<script>send(cookie)</script>" },
    { "id": "server", "type": "box", "label": "השרת שומר את התגובה" },
    { "id": "victim", "type": "box", "label": "משתמש אחר טוען את הדף" },
    { "id": "sanitize", "type": "diamond", "label": "יש סניטציה?" },
    { "id": "run", "type": "box", "label": "הסקריפט רץ בדפדפן הקורבן" },
    { "id": "steal", "type": "box", "label": "העוגייה נשלחת לתוקף" },
    { "id": "safe", "type": "box", "label": "התוכן מוצג כטקסט בלבד" }
  ],
  "connections": [
    { "from": "attacker", "to": "payload" },
    { "from": "payload", "to": "server" },
    { "from": "server", "to": "victim", "label": "הדף כולל את התגובה" },
    { "from": "victim", "to": "sanitize" },
    { "from": "sanitize", "to": "run", "label": "לא" },
    { "from": "run", "to": "steal" },
    { "from": "sanitize", "to": "safe", "label": "כן", "side": "right" }
  ],
  "animation": {
    "step_seconds": 1.5,
    "steps": [
      { "active": ["attacker"] },
      { "active": ["payload"], "edges": [0] },
      { "active": ["server"], "edges": [1] },
      { "active": ["victim"], "edges": [2] },
      { "active": ["sanitize"], "edges": [3] },
      { "active": ["safe"], "edges": [6] },
      { "active": ["sanitize"] },
      { "active": ["run"], "edges": [4] },
      { "active": ["steal"], "edges": [5] }
    ]
  }
}
