{
  "title": "התנאי באסמבלי הפוך מהתנאי בשפת C: התנאי x > 5 מתורגם לקפיצה jle שמדלגת אל ה-else כאשר x קטן או שווה לחמש",
  "layout": { "type": "flow" },
  "components": [
    { "id": "src", "type": "code", "label": "if (x > 5)", "values": ["if (x > 5)", "x = 3"] },
    { "id": "cmp", "type": "code", "label": "cmp edi, 5", "values": ["cmp edi, 5", "cmp 3, 5"] },
    { "id": "jle", "type": "diamond", "label": "jle .else", "values": ["jle .else", "3 <= 5 ?"] },
    { "id": "ifb", "type": "box", "label": "גוף ה-if" },
    { "id": "elseb", "type": "box", "label": "גוף ה-else" },
    { "id": "end", "type": "box", "label": "המשך התוכנית" }
  ],
  "connections": [
    { "from": "src", "to": "cmp" },
    { "from": "cmp", "to": "jle" },
    { "from": "jle", "to": "ifb", "label": "לא" },
    { "from": "jle", "to": "elseb", "label": "כן", "side": "right" },
    { "from": "ifb", "to": "end" },
    { "from": "elseb", "to": "end" }
  ],
  "animation": {
    "step_seconds": 1.8,
    "steps": [
      { "active": ["src"], "set": { "src": 1 } },
      { "active": ["cmp"], "edges": [0], "set": { "cmp": 1 } },
      { "active": ["jle"], "edges": [1], "set": { "jle": 1 } },
      { "active": ["elseb"], "edges": [3] },
      { "active": ["end"], "edges": [5] }
    ]
  }
}
