{
  "title": "תרשים זרימה: WAF בודק כל בקשת HTTP הנכנסת, ואם מזוהה בה תבנית תקיפה ידועה הוא חוסם אותה לפני שהיא מגיעה לאפליקציה",
  "layout": { "type": "flow" },
  "components": [
    { "id": "client", "type": "box", "label": "בקשת HTTP מגיעה מהמשתמש" },
    { "id": "waf", "type": "box", "label": "WAF בודק את תוכן הבקשה" },
    { "id": "check", "type": "diamond",
      "label": "זוהתה תבנית תקיפה?",
      "values": ["זוהתה תבנית תקיפה?", "כן - זוהתה תקיפה"] },
    { "id": "block", "type": "box", "label": "הבקשה נחסמת" },
    { "id": "app", "type": "box", "label": "האפליקציה מקבלת בקשה תקינה" }
  ],
  "connections": [
    { "from": "client", "to": "waf" },
    { "from": "waf", "to": "check" },
    { "from": "check", "to": "block", "label": "כן", "side": "right" },
    { "from": "check", "to": "app", "label": "לא" }
  ],
  "animation": {
    "step_seconds": 1.7,
    "steps": [
      { "active": ["client"] },
      { "active": ["waf"], "edges": [0] },
      { "active": ["check"], "edges": [1] },
      { "active": ["block"], "edges": [2], "set": { "check": 1 } }
    ]
  }
}
