{
  "title": "המסלול של מחלקה בקובץ CSS Module מזמן הכתיבה דרך הוספת ה-hash בזמן build ועד ה-DOM",
  "layout": { "type": "flow" },
  "components": [
    { "id": "src", "type": "code", "lines": ["/* Card.module.css */", ".card { padding: 16px }"] },
    { "id": "vite", "type": "box", "label": "Vite מזהה את הסיומת module.css" },
    { "id": "hash", "type": "code", "label": ".Card_card_x7g3k { padding: 16px }" },
    { "id": "obj", "type": "code", "label": "styles = { card: \"Card_card_x7g3k\" }" },
    { "id": "jsx", "type": "code", "label": "<div className={styles.card}>" },
    { "id": "dom", "type": "box", "label": "ב-DOM מופיע שם ייחודי - אין התנגשות" }
  ],
  "connections": [
    { "from": "src", "to": "vite" },
    { "from": "vite", "to": "hash" },
    { "from": "hash", "to": "obj" },
    { "from": "obj", "to": "jsx" },
    { "from": "jsx", "to": "dom" }
  ],
  "animation": {
    "step_seconds": 1.8,
    "steps": [
      { "active": ["src"] },
      { "active": ["vite"], "edges": [0] },
      { "active": ["hash"], "edges": [1] },
      { "active": ["obj"], "edges": [2] },
      { "active": ["jsx"], "edges": [3] },
      { "active": ["dom"], "edges": [4] }
    ]
  }
}
